podcast_transcript/__init__.py
podcast_transcript/audio.py
podcast_transcript/backends.py
podcast_transcript/config.py
podcast_transcript/single_track.py
podcast_transcript-0.1.5.dist-info/METADATA
podcast_transcript-0.1.5.dist-info/WHEEL
podcast_transcript-0.1.5.dist-info/entry_points.txt
podcast_transcript-0.1.5.dist-info/licenses/LICENSE
podcast_transcript-0.1.5.dist-info/RECORD
