Metadata-Version: 2.4
Name: podcast-transcript
Version: 0.1.5
Summary: Just a simple podcast transcript generator
Author-email: Jochen Wersdörfer <jochen@wersdoerfer.de>
License-File: LICENSE
Requires-Python: >=3.10
Requires-Dist: httpx>=0.27
Requires-Dist: rich>=13
Provides-Extra: mlx
Requires-Dist: mlx-whisper; (platform_system == 'Darwin' and platform_machine == 'arm64') and extra == 'mlx'
